evalme/__init__.py
evalme/classification.py
evalme/eval_item.py
evalme/matcher.py
evalme/metrics.py
evalme/utils.py
evalme/image/__init__.py
evalme/image/object_detection.py
evalme/tests/__init__.py
evalme/tests/test_classification.py
evalme/tests/test_matcher.py
evalme/tests/test_metrics.py
evalme/tests/test_object_detection.py
evalme/tests/test_old_format.py
evalme/tests/test_paragrahlabels.py
evalme/tests/test_text.py
evalme/text/__init__.py
evalme/text/text.py
label_studio_evalme-0.0.18.dist-info/LICENSE
label_studio_evalme-0.0.18.dist-info/METADATA
label_studio_evalme-0.0.18.dist-info/WHEEL
label_studio_evalme-0.0.18.dist-info/top_level.txt
label_studio_evalme-0.0.18.dist-info/RECORD
