Metadata-Version: 2.1
Name: label-studio-evalme
Version: 0.0.18
Summary: Evaluation metrics
Home-page: https://github.com/heartexlabs/label-studio-evalme
Author: Heartex
Author-email: hello@heartex.ai
License: UNKNOWN
Platform: UNKNOWN
Classifier: Programming Language :: Python :: 3
Classifier: License :: OSI Approved :: MIT License
Classifier: Operating System :: OS Independent
Requires-Python: >=3.6
License-File: LICENSE
Requires-Dist: Shapely (==1.7.1)
Requires-Dist: textdistance (==4.1.5)
Requires-Dist: attrs (>=19.2.0)
Requires-Dist: numpy (>=1.19.5)
Requires-Dist: requests (==2.25.1)
Requires-Dist: scipy (==1.4.1)
Requires-Dist: attr (==0.3.1)
Requires-Dist: xmljson (==0.2.0)
Requires-Dist: lxml (>=4.2.5)
Requires-Dist: label-studio-converter (==0.0.33rc5)
